arithmeticmeancurve.py
arithmeticmeancurve-0.3.2b2.dist-info/LICENSE.md
arithmeticmeancurve-0.3.2b2.dist-info/METADATA
arithmeticmeancurve-0.3.2b2.dist-info/WHEEL
arithmeticmeancurve-0.3.2b2.dist-info/top_level.txt
arithmeticmeancurve-0.3.2b2.dist-info/RECORD
