Metadata-Version: 2.1
Name: arithmeticmeancurve
Version: 0.3.2b2
Summary: Module for calculating an arithmetic mean curve from a family of curves.
Home-page: https://gitlab.com/david.scheliga/arithmeticmeancurve
Author: David Scheliga
Author-email: david.scheliga@gmx.de
License: GNU General Public License V3 (GPLv3)
Project-URL: Documentation, https://arithmeticmeancurve.readthedocs.io/en/latest/
Project-URL: Source Code Repository, https://gitlab.com/david.scheliga/arithmeticmeancurve
Keywords: pandas,arithmetic,curve
Platform: UNKNOWN
Classifier: Development Status :: 4 - Beta
Classifier: License :: OSI Approved :: GNU General Public License v3 (GPLv3)
Classifier: Operating System :: OS Independent
Classifier: Programming Language :: Python :: 3
Classifier: Programming Language :: Python :: 3.6
Classifier: Programming Language :: Python :: 3.7
Classifier: Programming Language :: Python :: 3.8
Classifier: Programming Language :: Python :: 3.9
Requires-Python: >=3.6
Requires-Dist: pandas (>=1.0.0)
Requires-Dist: numpy (>=1.16.0)
Requires-Dist: trashpanda (>=1.0.0)
Requires-Dist: matplotlib
Requires-Dist: scipy
Requires-Dist: examplecurves (>=1.0.0)
